Metadata-Version: 2.1
Name: resparser
Version: 0.4
Summary: Extract Resume Entities Using NER
Author: Yash Sonwane
License: UNKNOWN
Platform: UNKNOWN
